.gitmodules
CMakeLists.txt
LICENSE
MANIFEST.in
README.md
requirements.txt
setup.py
tox.ini
lib/HomLib/LICENSE
lib/HomLib/Makefile
lib/HomLib/README.md
lib/HomLib/example.cpp
lib/HomLib/includes/HomLib/get_fitzgibbon_cvpr_2001.hpp
lib/HomLib/includes/HomLib/get_kukelova_cvpr_2015.hpp
lib/HomLib/includes/HomLib/get_valtonenornhag_arxiv_2020a.hpp
lib/HomLib/includes/HomLib/get_valtonenornhag_arxiv_2020b.hpp
lib/HomLib/includes/HomLib/posedata.hpp
lib/HomLib/matlab/compile_mex.m
lib/HomLib/matlab/src/get_fitzgibbon_cvpr_2001_mex.cpp
lib/HomLib/matlab/src/get_kukelova_cvpr_2015_mex.cpp
lib/HomLib/matlab/src/get_valtonenornhag_arxiv_2020a_fHf_mex.cpp
lib/HomLib/matlab/src/get_valtonenornhag_arxiv_2020b_fHf_mex.cpp
lib/HomLib/matlab/src/get_valtonenornhag_arxiv_2020b_frHfr_mex.cpp
lib/HomLib/src/helpers/generate_problem_instance.cpp
lib/HomLib/src/helpers/generate_problem_instance.hpp
lib/HomLib/src/helpers/gj.cpp
lib/HomLib/src/helpers/gj.hpp
lib/HomLib/src/helpers/normalize2dpts.cpp
lib/HomLib/src/helpers/normalize2dpts.hpp
lib/HomLib/src/helpers/problem_instance.hpp
lib/HomLib/src/helpers/radial.cpp
lib/HomLib/src/helpers/radial.hpp
lib/HomLib/src/helpers/roots.cpp
lib/HomLib/src/helpers/roots.hpp
lib/HomLib/src/solvers/fitzgibbon_cvpr_2001/get_fitzgibbon_cvpr_2001.cpp
lib/HomLib/src/solvers/kukelova_cvpr_2015/get_kukelova_cvpr_2015.cpp
lib/HomLib/src/solvers/kukelova_cvpr_2015/solver_kukelova_cvpr_2015.cpp
lib/HomLib/src/solvers/kukelova_cvpr_2015/solver_kukelova_cvpr_2015.hpp
lib/HomLib/src/solvers/valtonenornhag_arxiv_2020a/get_valtonenornhag_arxiv_2020a_fHf.cpp
lib/HomLib/src/solvers/valtonenornhag_arxiv_2020a/solver_valtonenornhag_arxiv_2020a_fHf.cpp
lib/HomLib/src/solvers/valtonenornhag_arxiv_2020a/solver_valtonenornhag_arxiv_2020a_fHf.hpp
lib/HomLib/src/solvers/valtonenornhag_arxiv_2020b/get_valtonenornhag_arxiv_2020b_fHf.cpp
lib/HomLib/src/solvers/valtonenornhag_arxiv_2020b/get_valtonenornhag_arxiv_2020b_frHfr.cpp
src/homlib.egg-info/PKG-INFO
src/homlib.egg-info/SOURCES.txt
src/homlib.egg-info/dependency_links.txt
src/homlib.egg-info/not-zip-safe
src/homlib.egg-info/requires.txt
src/homlib.egg-info/top_level.txt
